pyfloyd/__init__.py
pyfloyd/__main__.py
pyfloyd/analyzer.py
pyfloyd/api.py
pyfloyd/formatter.py
pyfloyd/generator.py
pyfloyd/host.py
pyfloyd/interpreter.py
pyfloyd/javascript_generator.py
pyfloyd/parser.py
pyfloyd/printer.py
pyfloyd/py.typed
pyfloyd/python_generator.py
pyfloyd/string_literal.py
pyfloyd/tool.py
pyfloyd/version.py
pyfloyd-0.18.4.dist-info/LICENSE
pyfloyd-0.18.4.dist-info/METADATA
pyfloyd-0.18.4.dist-info/WHEEL
pyfloyd-0.18.4.dist-info/entry_points.txt
pyfloyd-0.18.4.dist-info/top_level.txt
pyfloyd-0.18.4.dist-info/RECORD
